odoo/addons/cooperator_website/README.rst
odoo/addons/cooperator_website/__init__.py
odoo/addons/cooperator_website/__manifest__.py
odoo/addons/cooperator_website/controllers/__init__.py
odoo/addons/cooperator_website/controllers/main.py
odoo/addons/cooperator_website/i18n/ca.po
odoo/addons/cooperator_website/i18n/ca_ES.po
odoo/addons/cooperator_website/i18n/cooperator_website.pot
odoo/addons/cooperator_website/i18n/de.po
odoo/addons/cooperator_website/i18n/es.po
odoo/addons/cooperator_website/i18n/fr.po
odoo/addons/cooperator_website/i18n/it.po
odoo/addons/cooperator_website/readme/CONTRIBUTORS.rst
odoo/addons/cooperator_website/readme/DESCRIPTION.rst
odoo/addons/cooperator_website/readme/HISTORY.rst
odoo/addons/cooperator_website/static/description/icon.png
odoo/addons/cooperator_website/static/description/index.html
odoo/addons/cooperator_website/static/src/js/cooperator.js
odoo/addons/cooperator_website/views/subscription_template.xml
odoo_addon_cooperator_website-16.0.1.0.0.9.dist-info/METADATA
odoo_addon_cooperator_website-16.0.1.0.0.9.dist-info/WHEEL
odoo_addon_cooperator_website-16.0.1.0.0.9.dist-info/top_level.txt
odoo_addon_cooperator_website-16.0.1.0.0.9.dist-info/RECORD
